fastapi_scaff/__init__.py
fastapi_scaff/__main__.py
fastapi_scaff/_api_tpl.json
fastapi_scaff/_project_tpl.json
fastapi_scaff-0.9.0.dist-info/licenses/LICENSE
fastapi_scaff-0.9.0.dist-info/METADATA
fastapi_scaff-0.9.0.dist-info/WHEEL
fastapi_scaff-0.9.0.dist-info/entry_points.txt
fastapi_scaff-0.9.0.dist-info/top_level.txt
fastapi_scaff-0.9.0.dist-info/RECORD
