Metadata-Version: 2.4
Name: fastapi-scaff
Version: 0.9.0
Summary: This is a fastapi scaff.
Author-email: axiner <atpuxiner@163.com>
Project-URL: Homepage, https://github.com/atpuxiner/fastapi-scaff
Classifier: Programming Language :: Python :: 3.11
Classifier: Operating System :: OS Independent
Requires-Python: >=3.11
License-File: LICENSE
Dynamic: license-file
